grand_lantern/Model.py
grand_lantern/__init__.py
grand_lantern/dataiterators/DatasetIterators.py
grand_lantern/dataiterators/Datasets.py
grand_lantern/dataiterators/__init__.py
grand_lantern/layers/Activation.py
grand_lantern/layers/Layers.py
grand_lantern/layers/__init__.py
grand_lantern/matrix/Matrix.py
grand_lantern/matrix/__init__.py
grand_lantern/metrics/Loss.py
grand_lantern/metrics/Metric.py
grand_lantern/metrics/__init__.py
grand_lantern/optimizers/Optimizers.py
grand_lantern/optimizers/__init__.py
grandlantern/Model.py
grandlantern/__init__.py
grandlantern/dataiterators/DatasetIterators.py
grandlantern/dataiterators/Datasets.py
grandlantern/dataiterators/__init__.py
grandlantern/layers/Activation.py
grandlantern/layers/Layers.py
grandlantern/layers/Regularizers.py
grandlantern/layers/__init__.py
grandlantern/matrix/Matrix.py
grandlantern/matrix/__init__.py
grandlantern/metrics/Loss.py
grandlantern/metrics/Metric.py
grandlantern/metrics/__init__.py
grandlantern/optimizers/Optimizers.py
grandlantern/optimizers/__init__.py
grandlantern-0.0.21.dist-info/LICENCE
grandlantern-0.0.21.dist-info/METADATA
grandlantern-0.0.21.dist-info/WHEEL
grandlantern-0.0.21.dist-info/top_level.txt
grandlantern-0.0.21.dist-info/RECORD
