Metadata-Version: 2.1
Name: grandlantern
Version: 0.0.21
Summary: This is the small library for deep learning.
Home-page: https://github.com/grand-yarl/grand_lantern
Author: grandyarl
Author-email: grand_yarl@mail.com
License: UNKNOWN
Project-URL: GitHub, https://github.com/grand-yarl/grand_lantern
Keywords: deeplearn
Platform: UNKNOWN
Classifier: Programming Language :: Python :: 3.9
Classifier: License :: OSI Approved :: MIT License
Classifier: Operating System :: OS Independent
Requires-Python: >=3.6
License-File: LICENCE
